og_proto/agent_server_pb2.py
og_proto/agent_server_pb2.pyi
og_proto/agent_server_pb2_grpc.py
og_proto/common_pb2.py
og_proto/common_pb2.pyi
og_proto/common_pb2_grpc.py
og_proto/kernel_server_pb2.py
og_proto/kernel_server_pb2.pyi
og_proto/kernel_server_pb2_grpc.py
og_proto/memory_pb2.py
og_proto/memory_pb2.pyi
og_proto/memory_pb2_grpc.py
og_proto/prompt_pb2.py
og_proto/prompt_pb2.pyi
og_proto/prompt_pb2_grpc.py
og_proto-0.5.3.dist-info/METADATA
og_proto-0.5.3.dist-info/WHEEL
og_proto-0.5.3.dist-info/top_level.txt
og_proto-0.5.3.dist-info/RECORD
