Metadata-Version: 2.1
Name: og-proto
Version: 0.5.3
Summary: Open source code interpreter agent for LLM
Home-page: https://github.com/dbpunk-labs/octogen
Author: imotai
Author-email: codego.me@gmail.com
Requires-Dist: grpc-google-iam-v1 >=0.12.0
Requires-Dist: grpcio-tools >=1.40.0
